setup.py
pymatuning/__init__.py
pymatuning/cli.py
pymatuning/listings.py
pymatuning/name_styles.py
pymatuning.egg-info/PKG-INFO
pymatuning.egg-info/SOURCES.txt
pymatuning.egg-info/dependency_links.txt
pymatuning.egg-info/entry_points.txt
pymatuning.egg-info/requires.txt
pymatuning.egg-info/top_level.txt
pymatuning/renderers/__init__.py
pymatuning/renderers/json.py
pymatuning/renderers/orgmode.py