Metadata-Version: 1.0
Name: pymatuning
Version: 0.1
Summary: Small python library and CLI for generating todos from python modules
Home-page: https://github.com/salotz/pymatuning
Author: Samuel D. Lotz
Author-email: samuel.lotz@salotz.info
License: UNKNOWN
Platform: UNKNOWN
